requirements.txt
setup.py
django_staff_required/__init__.py
django_staff_required/views.py
django_staff_required.egg-info/PKG-INFO
django_staff_required.egg-info/SOURCES.txt
django_staff_required.egg-info/dependency_links.txt
django_staff_required.egg-info/requires.txt
django_staff_required.egg-info/top_level.txt