Metadata-Version: 2.1
Name: django-staff-required
Version: 2020.7.1
Summary: Django StaffRequiredMixin - request.user.is_staff==True required
Home-page: https://github.com/andrewp-as-is/django-staff-required.py
License: Unlicense
Keywords: django staff
Platform: UNKNOWN
Classifier: Framework :: Django
Classifier: License :: Public Domain
Classifier: Operating System :: OS Independent
Classifier: Programming Language :: Python :: 3
